LICENSE
MANIFEST.in
README.md
setup.cfg
setup.py
django_osgeo_importer.egg-info/PKG-INFO
django_osgeo_importer.egg-info/SOURCES.txt
django_osgeo_importer.egg-info/dependency_links.txt
django_osgeo_importer.egg-info/not-zip-safe
django_osgeo_importer.egg-info/requires.txt
django_osgeo_importer.egg-info/top_level.txt
osgeo_importer/__init__.py
osgeo_importer/__init__.pyc
osgeo_importer/admin.py
osgeo_importer/admin.pyc
osgeo_importer/api.py
osgeo_importer/api.pyc
osgeo_importer/forms.py
osgeo_importer/forms.pyc
osgeo_importer/geonode_apis.py
osgeo_importer/geonode_apis.pyc
osgeo_importer/importers.py
osgeo_importer/importers.pyc
osgeo_importer/inspectors.py
osgeo_importer/inspectors.pyc
osgeo_importer/models.py
osgeo_importer/models.pyc
osgeo_importer/tasks.py
osgeo_importer/tasks.pyc
osgeo_importer/test_views.pyc
osgeo_importer/tests.pyc
osgeo_importer/urls.py
osgeo_importer/urls.pyc
osgeo_importer/utils.py
osgeo_importer/utils.pyc
osgeo_importer/validators.py
osgeo_importer/validators.pyc
osgeo_importer/views.py
osgeo_importer/views.pyc
osgeo_importer/handlers/__init__.py
osgeo_importer/handlers/__init__.pyc
osgeo_importer/handlers/geonode/__init__.py
osgeo_importer/handlers/geonode/__init__.pyc
osgeo_importer/handlers/geonode/backward_compatibility.py
osgeo_importer/handlers/geonode/backward_compatibility.pyc
osgeo_importer/handlers/geonode/publish_handler.py
osgeo_importer/handlers/geonode/publish_handler.pyc
osgeo_importer/handlers/geoserver/__init__.py
osgeo_importer/handlers/geoserver/__init__.pyc
osgeo_importer/handlers/mapproxy/__init__.py
osgeo_importer/handlers/mapproxy/conf_geopackage.py
osgeo_importer/handlers/mapproxy/publish_handler.py
osgeo_importer/migrations/0001_initial.py
osgeo_importer/migrations/0001_initial.pyc
osgeo_importer/migrations/0002_auto_20160713_1429.py
osgeo_importer/migrations/0002_auto_20160713_1429.pyc
osgeo_importer/migrations/0003_uploadlayer_upload_file.py
osgeo_importer/migrations/0003_uploadlayer_upload_file.pyc
osgeo_importer/migrations/0004_uploadfile_file_type.py
osgeo_importer/migrations/0004_uploadfile_file_type.pyc
osgeo_importer/migrations/0005_uploadlayer_layer_name.py
osgeo_importer/migrations/0005_uploadlayer_layer_name.pyc
osgeo_importer/migrations/0006_auto_20161007_1723.py
