Metadata-Version: 1.1
Name: django-osgeo-importer
Version: 0.2.1
Summary: django-osgeo-importer is a reusable Django application for inspecting geospatial data using GDAL/OGR and importing the data into an application.
Home-page: https://github.com/GeoNode/django-osgeo-importer
Author: django-osgeo-importer contributors
Author-email: garnertb@prominentedge.com
License: GPLv3+
Platform: UNKNOWN
Classifier: Development Status :: 3 - Alpha
Classifier: Environment :: Web Environment
Classifier: Intended Audience :: Developers
Classifier: License :: OSI Approved :: GNU General Public License v3 or later (GPLv3+)
Classifier: Operating System :: POSIX :: Linux
Classifier: Programming Language :: Python :: 2.7
Classifier: Framework :: Django :: 1.8
